{
    "2015": {
        "11": {
            "penalty": 1,
            "penalty_yds": 5
        },
        "10": {},
        "13": {
            "penalty": 1,
            "penalty_yds": 10
        },
        "12": {
            "penalty": 1,
            "penalty_yds": 5
        },
        "15": {
            "kickret_lngtd": 0,
            "kickret_lng": 0,
            "kickret_yds": 0,
            "kickret_avg": 0,
            "kickret_tds": 0,
            "kickret_ret": 1
        },
        "14": {
            "defense_tkl": 1
        },
        "17": {
            "kickret_yds": 9,
            "kickret_ret": 1,
            "kickret_lngtd": 0,
            "kickret_lng": 9,
            "kickret_avg": 9,
            "kickret_tds": 0
        },
        "16": {
            "defense_tkl": 1
        },
        "1": {},
        "3": {},
        "2": {},
        "5": {},
        "4": {},
        "7": {},
        "6": {
            "BYE": true
        },
        "9": {},
        "8": {
            "defense_tkl": 1
        }
    }
}