{
    "2015": {
        "11": {
            "kicking_fgm_yds": 24,
            "kicking_all_yds": 75,
            "kicking_fgm_0_39": 1,
            "kicking_totpfg": 3,
            "kicking_xptot": 2,
            "kicking_tot": 3,
            "kicking_touchback": 1,
            "kicking_xpmissed": 0,
            "kicking_xpmade": 2,
            "kicking_yds": 204,
            "kicking_fga": 1,
            "kicking_fgm": 1,
            "kicking_xpa": 2,
            "kicking_xpb": 0,
            "kicking_fgyds": 24
        },
        "10": {
            "kicking_xpmissed": 0,
            "kicking_totpfg": 0,
            "kicking_xptot": 1,
            "kicking_tot": 3,
            "kicking_xpmade": 1,
            "kicking_yds": 34,
            "kicking_fga": 0,
            "kicking_fgm": 0,
            "kicking_xpa": 1,
            "kicking_xpb": 0,
            "kicking_fgyds": 0
        },
        "13": {
            "kicking_fgm_yds": 23,
            "kicking_all_yds": 220,
            "kicking_fgm_0_39": 1,
            "kicking_totpfg": 3,
            "kicking_xptot": 2,
            "kicking_fgmissed_yds": 52,
            "kicking_tot": 4,
            "kicking_touchback": 3,
            "kicking_xpmissed": 0,
            "kicking_xpmade": 2,
            "kicking_yds": 260,
            "kicking_fga": 2,
            "kicking_fgm": 1,
            "kicking_fgmissed": 1,
            "kicking_xpa": 2,
            "kicking_xpb": 0,
            "kicking_fgyds": 23
        },
        "12": {
            "kicking_fgm_yds": 21,
            "kicking_all_yds": 450,
            "kicking_fgm_0_39": 1,
            "kicking_totpfg": 3,
            "kicking_xptot": 3,
            "kicking_fgmissed_yds": 47,
            "kicking_tot": 6,
            "kicking_touchback": 6,
            "kicking_xpmissed": 0,
            "kicking_xpmade": 3,
            "kicking_yds": 390,
            "kicking_fga": 2,
            "kicking_fgm": 1,
            "kicking_fgmissed": 1,
            "kicking_xpa": 3,
            "kicking_xpb": 0,
            "kicking_fgyds": 21
        },
        "15": {
            "kicking_all_yds": 222,
            "kicking_xpmissed": 1,
            "kicking_totpfg": 0,
            "kicking_xptot": 3,
            "kicking_tot": 5,
            "kicking_touchback": 3,
            "kicking_xpmade": 3,
            "kicking_yds": 327,
            "kicking_fga": 0,
            "kicking_fgm": 0,
            "kicking_xpa": 4,
            "kicking_xpb": 0,
            "kicking_fgyds": 0
        },
        "14": {
            "kicking_fgm_yds": 125,
            "kicking_all_yds": 297,
            "kicking_fgm_0_39": 3,
            "kicking_totpfg": 12,
            "kicking_xptot": 0,
            "kicking_fgmissed_yds": 49,
            "kicking_tot": 5,
            "kicking_touchback": 4,
            "kicking_xpmissed": 0,
            "kicking_xpmade": 0,
            "kicking_yds": 331,
            "kicking_fgm_40_49": 1,
            "kicking_fga": 5,
            "kicking_fgm": 4,
            "kicking_fgmissed": 1,
            "kicking_xpa": 0,
            "kicking_xpb": 0,
            "kicking_fgyds": 41
        },
        "17": {
            "kicking_fgm_yds": 83,
            "kicking_all_yds": 374,
            "kicking_fgm_0_39": 1,
            "kicking_totpfg": 6,
            "kicking_xptot": 3,
            "kicking_tot": 6,
            "kicking_touchback": 5,
            "kicking_xpmissed": 0,
            "kicking_xpmade": 3,
            "kicking_yds": 387,
            "kicking_fgm_40_49": 1,
            "kicking_fga": 2,
            "kicking_fgm": 2,
            "kicking_xpa": 3,
            "kicking_xpb": 0,
            "kicking_fgyds": 48
        },
        "16": {
            "kicking_fgm_yds": 60,
            "kicking_all_yds": 221,
            "kicking_fgm_0_39": 2,
            "kicking_totpfg": 6,
            "kicking_xptot": 2,
            "kicking_fgmissed_yds": 45,
            "kicking_tot": 5,
            "kicking_touchback": 3,
            "kicking_xpmissed": 0,
            "kicking_xpmade": 2,
            "kicking_yds": 298,
            "kicking_fga": 3,
            "kicking_fgm": 2,
            "kicking_fgmissed": 1,
            "kicking_xpa": 2,
            "kicking_xpb": 0,
            "kicking_fgyds": 37
        },
        "1": {
            "kicking_fgm_yds": 189,
            "kicking_all_yds": 373,
            "kicking_fgm_0_39": 1,
            "kicking_totpfg": 12,
            "kicking_xptot": 1,
            "kicking_tot": 6,
            "kicking_touchback": 5,
            "kicking_xpmissed": 0,
            "kicking_xpmade": 1,
            "kicking_yds": 365,
            "kicking_fgm_40_49": 1,
            "kicking_fga": 4,
            "kicking_fgm_50_100": 2,
            "kicking_fgm": 4,
            "kicking_xpa": 1,
            "kicking_xpb": 0,
            "kicking_fgyds": 57
        },
        "3": {
            "kicking_fgm_yds": 48,
            "kicking_all_yds": 365,
            "kicking_totpfg": 3,
            "kicking_xptot": 3,
            "kicking_tot": 5,
            "kicking_touchback": 5,
            "kicking_xpmissed": 0,
            "kicking_xpmade": 3,
            "kicking_yds": 325,
            "kicking_fgm_40_49": 1,
            "kicking_fga": 1,
            "kicking_fgm": 1,
            "kicking_xpa": 3,
            "kicking_xpb": 0,
            "kicking_fgyds": 48
        },
        "2": {
            "kicking_i20": 1,
            "kicking_fgm_yds": 54,
            "kicking_all_yds": 339,
            "kicking_totpfg": 3,
            "kicking_xptot": 4,
            "kicking_tot": 6,
            "kicking_touchback": 5,
            "kicking_xpmissed": 0,
            "kicking_xpmade": 4,
            "kicking_yds": 395,
            "kicking_fga": 1,
            "kicking_fgm_50_100": 1,
            "kicking_fgm": 1,
            "kicking_xpa": 4,
            "kicking_xpb": 0,
            "kicking_fgyds": 54
        },
        "5": {
            "kicking_all_yds": 222,
            "kicking_xptot": 1,
            "kicking_touchback": 3,
            "punting_lng": 41,
            "kicking_fgm_50_100": 1,
            "kicking_xpa": 1,
            "kicking_xpb": 0,
            "kicking_fgyds": 52,
            "kicking_i20": 1,
            "kicking_xpmissed": 0,
            "punting_pts": 1,
            "kicking_tot": 5,
            "punting_avg": 21,
            "kicking_yds": 332,
            "punting_i20": 0,
            "kicking_totpfg": 9,
            "kicking_xpmade": 1,
            "punting_yds": 41,
            "punting_tot": 1,
            "kicking_fgm_yds": 97,
            "punting_touchback": 1,
            "kicking_fgm_0_39": 2,
            "kicking_fga": 3,
            "kicking_fgm": 3
        },
        "4": {
            "kicking_i20": 1,
            "kicking_fgm_yds": 119,
            "kicking_all_yds": 300,
            "kicking_fgm_0_39": 2,
            "kicking_totpfg": 9,
            "kicking_xptot": 2,
            "kicking_tot": 6,
            "kicking_touchback": 4,
            "kicking_xpmissed": 0,
            "kicking_xpmade": 2,
            "kicking_yds": 387,
            "kicking_fgm_40_49": 1,
            "kicking_fga": 3,
            "kicking_fgm": 3,
            "kicking_xpa": 2,
            "kicking_xpb": 0,
            "kicking_fgyds": 47
        },
        "7": {
            "BYE": true
        },
        "6": {
            "kicking_i20": 1,
            "kicking_fgm_yds": 127,
            "kicking_all_yds": 150,
            "kicking_fgm_0_39": 4,
            "kicking_totpfg": 12,
            "kicking_xptot": 2,
            "kicking_fgmissed_yds": 51,
            "kicking_tot": 6,
            "kicking_touchback": 2,
            "kicking_xpmissed": 0,
            "kicking_xpmade": 2,
            "kicking_yds": 378,
            "kicking_fga": 5,
            "kicking_fgm": 4,
            "kicking_fgmissed": 1,
            "kicking_xpa": 2,
            "kicking_xpb": 0,
            "kicking_fgyds": 39
        },
        "9": {
            "kicking_fgm_yds": 29,
            "kicking_all_yds": 141,
            "kicking_fgm_0_39": 1,
            "kicking_totpfg": 3,
            "kicking_xptot": 3,
            "kicking_tot": 4,
            "kicking_touchback": 2,
            "kicking_xpmissed": 0,
            "kicking_xpmade": 3,
            "kicking_yds": 229,
            "kicking_xpb": 0,
            "kicking_fga": 1,
            "kicking_fgm": 1,
            "kicking_xpa": 3,
            "defense_ast": 1,
            "kicking_fgyds": 29
        },
        "8": {
            "kicking_i20": 2,
            "kicking_fgm_yds": 74,
            "kicking_all_yds": 293,
            "kicking_fgm_0_39": 1,
            "kicking_totpfg": 6,
            "kicking_xptot": 3,
            "kicking_tot": 6,
            "kicking_touchback": 4,
            "kicking_xpmissed": 0,
            "kicking_xpmade": 3,
            "kicking_yds": 404,
            "kicking_fga": 2,
            "kicking_fgm_50_100": 1,
            "kicking_fgm": 2,
            "kicking_xpa": 3,
            "kicking_xpb": 0,
            "kicking_fgyds": 50
        }
    },
    "2016": {
        "9": {
            "kicking_i20": 1,
            "kicking_fgm_yds": 99,
            "kicking_all_yds": 136,
            "kicking_totpfg": 6,
            "kicking_xptot": 2,
            "kicking_tot": 4,
            "kicking_touchback": 2,
            "kicking_xpmissed": 0,
            "kicking_xpmade": 2,
            "kicking_yds": 248,
            "kicking_fgm_40_49": 1,
            "kicking_fga": 2,
            "kicking_fgm_50_100": 1,
            "kicking_fgm": 2,
            "kicking_xpa": 2,
            "kicking_xpb": 0,
            "kicking_fgyds": 55
        },
        "10": {
            "kicking_i20": 1,
            "kicking_fgm_yds": 115,
            "kicking_all_yds": 287,
            "kicking_fgm_0_39": 2,
            "kicking_totpfg": 9,
            "kicking_xptot": 2,
            "kicking_fgmissed_yds": 42,
            "kicking_tot": 6,
            "kicking_touchback": 4,
            "kicking_xpmissed": 0,
            "kicking_xpmade": 2,
            "kicking_yds": 383,
            "defense_tkl": 1,
            "kicking_fga": 4,
            "kicking_fgm_50_100": 1,
            "kicking_fgm": 3,
            "kicking_fgmissed": 1,
            "kicking_xpa": 2,
            "kicking_xpb": 0,
            "kicking_fgyds": 50
        },
        "13": {
            "kicking_fgm_yds": 73,
            "kicking_all_yds": 214,
            "kicking_fgm_0_39": 1,
            "kicking_totpfg": 6,
            "kicking_xptot": 2,
            "kicking_tot": 5,
            "kicking_touchback": 3,
            "kicking_xpmissed": 0,
            "kicking_xpmade": 2,
            "kicking_yds": 254,
            "kicking_fgm_40_49": 1,
            "kicking_fga": 2,
            "kicking_fgm": 2,
            "kicking_xpa": 2,
            "kicking_xpb": 0,
            "kicking_fgyds": 41
        },
        "5": {
            "kicking_fgm_yds": 126,
            "kicking_all_yds": 146,
            "kicking_fgm_0_39": 1,
            "kicking_totpfg": 9,
            "kicking_xptot": 1,
            "kicking_fgm_40_49": 2,
            "kicking_tot": 5,
            "kicking_touchback": 2,
            "kicking_xpmissed": 0,
            "kicking_xpmade": 1,
            "kicking_yds": 208,
            "defense_tkl": 1,
            "kicking_fga": 3,
            "kicking_fgm": 3,
            "kicking_xpa": 1,
            "kicking_xpb": 0,
            "kicking_fgyds": 46
        },
        "14": {
            "kicking_i20": 1,
            "kicking_fgm_yds": 34,
            "kicking_all_yds": 75,
            "kicking_fgm_0_39": 1,
            "kicking_totpfg": 3,
            "kicking_xptot": 1,
            "kicking_tot": 3,
            "kicking_touchback": 1,
            "kicking_xpmissed": 0,
            "kicking_xpmade": 1,
            "kicking_yds": 209,
            "kicking_fga": 1,
            "kicking_fgm": 1,
            "kicking_xpa": 1,
            "kicking_xpb": 0,
            "kicking_fgyds": 34
        }
    }
}