{
    "rushing_tds": "6",
    "puntret_yds": "1",
    "rushing_yds": "0.1",
    "passing_yds_py5": "0.2",
    "kicking_fgm_40_49": "3",
    "kickret_tds": "6",
    "kicking_fgm_50_100": "4",
    "receiving_tds": "6",
    "kicking_xpmissed": "-2",
    "fumbles_lost": "-2",
    "kickret_yds": "1",
    "interception": "-2",
    "receiving_rec": "0.2",
    "receiving_yds": "0.1",
    "receiving_twoptm": "2",
    "rushing_twoptm": "2",
    "kicking_fgmissed_0_39": "-1",
    "passing_twoptm": "2",
    "defense_frec_tds": "6",
    "kicking_xpmade": "0.1",
    "puntret_tds": "6",
    "kicking_fgm_0_39": "2",
    "fumbles_frec_tds": "6",
    "defense": {
        "defense_YA_549": "-6",
        "defense_YA_99": "5",
        "defense_fpts": 1.0,
        "defense_frec": "2",
        "defense_blkk": "2",
        "kickret_tds": "6",
        "defense_YA_449": "-3",
        "defense_PA_0": "5",
        "defense_YA_550": "-7",
        "defense_safe": "2",
        "defense_PA_35_45": "-3",
        "interception": "2",
        "defense_sk": "1",
        "defense_PA_7_13": "3",
        "defense_PA_14_17": "1",
        "defense_rush": 0,
        "defense_PA_46": "-5",
        "defense_PA_28_34": "-1",
        "defense_PA_1_6": "4",
        "defense_YA_199": "3",
        "defense_frec_tds": "6",
        "defense_YA_499": "-5",
        "defense_blkkrtd": "6",
        "defense_YA_399": "-1",
        "defense_pass": 0,
        "puntret_tds": "6",
        "defense_int_tds": "6",
        "defense_YA_299": "2"
    },
    "passing_tds": "4"
}